LICENSE
MANIFEST.in
setup.cfg
setup.py
pylemonway/__init__.py
pylemonway/lexceptions.py
pylemonway/pylemonway.py
pylemonway.egg-info/PKG-INFO
pylemonway.egg-info/SOURCES.txt
pylemonway.egg-info/dependency_links.txt
pylemonway.egg-info/requires.txt
pylemonway.egg-info/top_level.txt