Metadata-Version: 1.1
Name: pylemonway
Version: 0.1.3
Summary: Python wrapper for Lemonway DIRECTKITJSON2
Home-page: https://github.com/acarmisc/pylemonway
Author: Andrea Carmisciano
Author-email: andrea.carmisciano@gmail.com
License: APACHE 2.0
Keywords: REST lemonway requests crowdfunding
Platform: UNKNOWN
Classifier: Development Status :: 4 - Beta
Classifier: Programming Language :: Python :: 2
Classifier: Programming Language :: Python :: 2.6
Classifier: Programming Language :: Python :: 2.7
Classifier: Programming Language :: Python :: 3
Classifier: Programming Language :: Python :: 3.3
Classifier: Programming Language :: Python :: 3.4
Classifier: Programming Language :: Python :: 3.5
